Metadata-Version: 1.1
Name: beautiful-ansi
Version: 0.1.7
Summary: ANSI escape code library
Home-page: https://github.com/Carrene/beautiful-ansi
Author: Mohammad Hasanzadeh
Author-email: mohammad@carrene.com
License: UNKNOWN
Keywords: ANSI escape code library
Platform: UNKNOWN
Classifier: Development Status :: 3 - Alpha
Classifier: Natural Language :: English
Classifier: Programming Language :: Python :: 2.7
Classifier: Programming Language :: Python :: 3.5
Classifier: Programming Language :: Python :: 3.6
Classifier: Topic :: Terminals
